pyspectrum/__init__.py
pyspectrum/color_examples.py
pyspectrum-0.1.5.dist-info/LICENSE
pyspectrum-0.1.5.dist-info/METADATA
pyspectrum-0.1.5.dist-info/WHEEL
pyspectrum-0.1.5.dist-info/top_level.txt
pyspectrum-0.1.5.dist-info/RECORD
