Metadata-Version: 2.1
Name: pyspectrum
Version: 0.1.5
Summary: a small, multi-use color library for python that supports RGB, Hexadecimal, Decimal, CMYK and most web colors
Home-page: https://github.com/gooseterv/pyspectrum
Author: GooseterV
Author-email: 82774618+GooseterV@users.noreply.github.com
License: UNKNOWN
Project-URL: Bug Tracker, https://github.com/gooseterv/pyspectrum/issues
Platform: UNKNOWN
Classifier: Programming Language :: Python :: 3
Classifier: License :: OSI Approved :: MIT License
Classifier: Operating System :: OS Independent
Requires-Python: >=3.6
License-File: LICENSE
